README.md
setup.py
EnforsML.egg-info/PKG-INFO
EnforsML.egg-info/SOURCES.txt
EnforsML.egg-info/dependency_links.txt
EnforsML.egg-info/requires.txt
EnforsML.egg-info/top_level.txt
enforsml/__init__.py
enforsml/image/__init__.py
enforsml/image/divide.py
enforsml/text/__init__.py
enforsml/text/bagofwords.py
enforsml/text/emlb.py
enforsml/text/ngram.py
enforsml/text/nlp.py
enforsml/text/utils.py
enforsml/text/word.py