Metadata-Version: 1.2
Name: EnforsML
Version: 0.0.3
Summary: A very small set of tools used for things related to machine learning.
Home-page: https://github.com/enfors/EnforsML
Author: Christer Enfors
Author-email: christer.enfors@gmail.com
License: LGPL
Platform: UNKNOWN
Requires-Python: >=3
